tigereye/__init__.py
tigereye/entry.py
tigereye/error.py
tigereye/load.py
tigereye/mgmt.py
tigereye/parse.py
tigereye/task.py
tigereye/tigereye.py
tigereye/util.py
tigereye-0.2.1.dist-info/METADATA
tigereye-0.2.1.dist-info/RECORD
tigereye-0.2.1.dist-info/WHEEL
tigereye-0.2.1.dist-info/entry_points.txt
tigereye-0.2.1.dist-info/top_level.txt
