Metadata-Version: 2.1
Name: tigereye
Version: 0.2.1
Summary: A reusable data-mainupulation and plotting tool
Home-page: https://github.com/grnydawn/tigereye
Author: Youngsung Kim
Author-email: grnydawn@gmail.com
License: MIT license
Keywords: tigereye
Platform: UNKNOWN
Classifier: Development Status :: 2 - Pre-Alpha
Classifier: Intended Audience :: Developers
Classifier: License :: OSI Approved :: MIT License
Classifier: Natural Language :: English
Classifier: Programming Language :: Python :: 2
Classifier: Programming Language :: Python :: 2.7
Classifier: Programming Language :: Python :: 3
Classifier: Programming Language :: Python :: 3.4
Classifier: Programming Language :: Python :: 3.5
Classifier: Programming Language :: Python :: 3.6
Requires-Dist: numpy
Requires-Dist: matplotlib
Requires-Dist: pandas
